ypyjson/__init__.py
ypyjson/reader.c
ypyjson/reader.cp39-win_amd64.pyd
ypyjson/reader.pxd
ypyjson/reader.pyi
ypyjson/reader.pyx
ypyjson/ypyflags.py
ypyjson/yyr.pxi
ypyjson/yyjson/yyjson.c
ypyjson/yyjson/yyjson.h
ypyjson-0.0.2.dist-info/LICENSE.txt
ypyjson-0.0.2.dist-info/METADATA
ypyjson-0.0.2.dist-info/WHEEL
ypyjson-0.0.2.dist-info/top_level.txt
ypyjson-0.0.2.dist-info/RECORD
