Metadata-Version: 2.1
Name: ypyjson
Version: 0.0.2
Summary: yet another python json library using yyjson
Author: Vizonex
License: Unlicense
Keywords: yyjson,ypyjson,json,cython
Classifier: Programming Language :: Python :: 3.9
Classifier: Programming Language :: Python :: 3.10
Classifier: Programming Language :: Python :: 3.11
License-File: LICENSE.txt
